[
  {
    "topic": "挽回爱情",
    "date": "2017-05-21 13:00",
    "user": {
      "name": "匿名用户1",
      "content": "爱情分手被断联，不会这一招，怎么挽回女人？说的就是你，你说说你怎么挽回你女人？你不能这么直啊，适当的时候要弯一下才行，俗话说的好，过刚则易折嘛，我说的在不在理儿？"
    },
    "mentors": [
      {
        "name": "嘉伟导师",
	"content": "爱情分手被断联，不会这招怎么挽回？"
      },
      {
        "name": "千芜导师",
	"content": "你的学会分析你自己的弱势和有事，扬长避短是王道。"
      },
      {
        "name": "杰尼导师",
	"content": "这个还得看自己才行啊，有时候别人帮不了你。"
      }
    ]
  },
  {
    "topic": "挽救婚姻",
    "date": "2018-06-21 14:00",
    "user": {
      "name": "匿名用户2",
      "content": "爱情分手被断联，不会这一招，怎么挽回女人？说的就是你，你说说你怎么挽回你女人？你不能这么直啊，适当的时候要弯一下才行，俗话说的好，过刚则易折嘛，我说的在不在理儿？"
    },
    "mentors": [
      {
        "name": "千芜导师",
	"content": "你的学会分析你自己的弱势和有事，扬长避短是王道。"
      },
      {
        "name": "杰尼导师",
	"content": "这个还得看自己才行啊，有时候别人帮不了你。"
      }
    ]
  },
  {
    "topic": "挽回爱情",
    "date": "2017-05-21 13:00",
    "user": {
      "name": "匿名用户1",
      "content": "爱情分手被断联，不会这一招，怎么挽回女人？说的就是你，你说说你怎么挽回你女人？你不能这么直啊，适当的时候要弯一下才行，俗话说的好，过刚则易折嘛，我说的在不在理儿？"
    },
    "mentors": [
      {
        "name": "嘉伟导师",
	"content": "爱情分手被断联，不会这招怎么挽回？"
      },
      {
        "name": "千芜导师",
	"content": "你的学会分析你自己的弱势和有事，扬长避短是王道。"
      },
      {
        "name": "杰尼导师",
	"content": "这个还得看自己才行啊，有时候别人帮不了你。"
      }
    ]
  },
  {
    "topic": "挽救婚姻",
    "date": "2018-06-21 14:00",
    "user": {
      "name": "匿名用户2",
      "content": "爱情分手被断联，不会这一招，怎么挽回女人？说的就是你，你说说你怎么挽回你女人？你不能这么直啊，适当的时候要弯一下才行，俗话说的好，过刚则易折嘛，我说的在不在理儿？"
    },
    "mentors": [
      {
        "name": "千芜导师",
	"content": "你的学会分析你自己的弱势和有事，扬长避短是王道。"
      },
      {
        "name": "杰尼导师",
	"content": "这个还得看自己才行啊，有时候别人帮不了你。"
      }
    ]
  }
]
